Metadata-Version: 2.1
Name: Turk-game
Version: 1.0.5
Summary: Türk profesyoneller ve acemiler için basitleştirilmiş ve kısaltılmış pygame
Home-page: 
Author: Eymen
Author-email: taneymen2009@gmail.com
License-File: LICENSE
